LICENSE
MANIFEST.in
README.md
pavement.py
setup.py
pytimeseries.egg-info/PKG-INFO
pytimeseries.egg-info/SOURCES.txt
pytimeseries.egg-info/dependency_links.txt
pytimeseries.egg-info/not-zip-safe
pytimeseries.egg-info/top_level.txt