Metadata-Version: 1.1
Name: pytimeseries
Version: 0.0.0
Summary: Time Series Forecasting using Python
Home-page: http://github.com/jdvelasq/pytimeseries
Author: Juan D. Velasquez & Alejandra Arango
Author-email: jdvelasq@unal.edu.co
License: MIT
Keywords: time-series forecast predict
Platform: UNKNOWN
Classifier: Development Status :: 3 - Alpha
Classifier: License :: OSI Approved :: MIT License
Classifier: Programming Language :: Python :: 3.5
Classifier: Topic :: Office/Business :: Financial
